texting/__init__.py
texting/bracket/__init__.py
texting/chars/__init__.py
texting/enum/__init__.py
texting/enum/brackets/__init__.py
texting/enum/quotes/__init__.py
texting/enum/regexes/__init__.py
texting/enum/regexes/strings/__init__.py
texting/fold/__init__.py
texting/has_ansi/__init__.py
texting/has_ansi/elements.py
texting/has_ansi/regs.py
texting/indexing/__init__.py
texting/lange/__init__.py
texting/lines/__init__.py
texting/pad/__init__.py
texting/phrasing/__init__.py
texting/ripper/__init__.py
texting/ripper/ripper.py
texting/ripper/split_literal.py
texting/str_util/__init__.py
texting/str_value/__init__.py
texting/tap/__init__.py
texting-0.0.13.dist-info/WHEEL
texting-0.0.13.dist-info/METADATA
texting-0.0.13.dist-info/RECORD
