Metadata-Version: 2.1
Name: texting
Version: 0.0.13
Summary: misc for string
Home-page: https://github.com/pydget/texting.git
License: MIT
Keywords: str,string,ansi,length,pad,tap,str_value,string_value
Author: Hoyeung Wong
Author-email: hoyeungw@outlook.com
Requires-Python: >=3.8,<4.0
Classifier: License :: OSI Approved :: MIT License
Classifier: Programming Language :: Python :: 3
Classifier: Programming Language :: Python :: 3.8
Classifier: Programming Language :: Python :: 3.9
Project-URL: Repository, https://github.com/pydget/texting.git
